polyline_rs-1.3.0.dist-info/RECORD
polyline_rs-1.3.0.dist-info/WHEEL
polyline_rs-1.3.0.dist-info/METADATA
polyline_rs/_lib.cpython-39-darwin.so
polyline_rs/__init__.py
polyline_rs/py.typed
polyline_rs/_lib.pyi
