Metadata-Version: 2.4
Name: polyline-rs
Version: 1.3.0
Classifier: Development Status :: 5 - Production/Stable
Classifier: Intended Audience :: Developers
Classifier: License :: OSI Approved :: Zero-Clause BSD (0BSD)
Classifier: Operating System :: OS Independent
Classifier: Programming Language :: Python :: 3.9
Classifier: Programming Language :: Python :: 3.10
Classifier: Programming Language :: Python :: 3.11
Classifier: Programming Language :: Python :: 3.12
Classifier: Programming Language :: Python :: 3.13
Classifier: Programming Language :: Python :: 3.14
Classifier: Programming Language :: Python :: Implementation :: CPython
Classifier: Programming Language :: Python :: Implementation :: PyPy
Classifier: Programming Language :: Rust
Classifier: Topic :: Software Development :: Libraries :: Python Modules
Classifier: Typing :: Typed
Summary: Fast Google Encoded Polyline encoding & decoding
Keywords: decoding,encoding,gis,google,mapbox,openstreetmap,polyline
Author-email: Kamil Monicz <kamil@monicz.dev>
License-Expression: 0BSD
Requires-Python: >=3.9
Project-URL: Issues, https://github.com/Zaczero/pkgs/issues
Project-URL: Repository, https://github.com/Zaczero/pkgs/tree/main/polyline-rs
